{"_via_settings":{"ui":{"annotation_editor_height":25,"annotation_editor_fontsize":0.8,"leftsidebar_width":18,"image_grid":{"img_height":80,"rshape_fill":"none","rshape_fill_opacity":0.3,"rshape_stroke":"yellow","rshape_stroke_width":2,"show_region_shape":true,"show_image_policy":"all"},"image":{"region_label":"region_id","region_label_font":"10px Sans"}},"core":{"buffer_size":18,"filepath":{},"default_filepath":""},"project":{"name":"via_project_24Jan2019_18h17m"}},"_via_img_metadata":{"http://10.5.0.142:9006/penn_in_hand/images/3071_2.jpg-1":{"filename":"http://10.5.0.142:9006/penn_in_hand/images/3071_2.jpg","size":-1,"regions":[{"shape_attributes":{"name":"rect","x":24,"y":48,"width":49,"height":47},"region_attributes":{"Spatial Annotation":"Library Marker","Comments":""},"timestamp":{}},{"shape_attributes":{"name":"circle","all_points_x":[139,131,127,123,125,128,137,204,213,215,215,170,150,144,140],"all_points_y":[45,48,52,59,64,67,72,71,68,63,46,41,41,46,45]},"region_attributes":{"Spatial Annotation":"Character Component","Comments":""},"timestamp":{"StartingTime":4112764,"EndTime":4116927}},{"shape_attributes":{"name":"polygon","all_points_x":[78,179,304,385,381,174,69],"all_points_y":[114,116,114,116,135,134,134]},"region_attributes":{"Spatial Annotation":"Character Line Segment","Comments":""},"timestamp":{"StartingTime":4121372,"EndTime":4129460}}],"file_attributes":{}}},"_via_attributes":{"region":{"Spatial Annotation":{"type":"dropdown","description":"","options":{"Hole(Virtual)":"","Hole(Physical)":"","Character Line Segment":"","Boundary Line":"","Physical Degradation":"","Page Boundary":"","Character Component":"","Library Marker":"","Picture / Decorator":""},"default_options":{}},"Comments":{"type":"text","description":"","default_value":""}},"file":{}},"file":"pih-7e7b10cb-a361-4faf-8621-675f1a9c6c8f"}